pyNutriScore/__init__.py
pyNutriScore/nutri_score.py
pyNutriScore/interfaces/__init__.py
pyNutriScore/interfaces/foodTypes.py
pyNutriScore/interfaces/nutrientTypes.py
pyNutriScore/interfaces/scoreTable.json
pyNutriScore/interfaces/scoreTableInterface.py
tests/__init__.py
tests/test_nutri_score.py
pyNutriScore-0.0.2.dist-info/LICENSE
pyNutriScore-0.0.2.dist-info/METADATA
pyNutriScore-0.0.2.dist-info/WHEEL
pyNutriScore-0.0.2.dist-info/top_level.txt
pyNutriScore-0.0.2.dist-info/RECORD
