Metadata-Version: 2.1
Name: pyNutriScore
Version: 0.0.2
Summary: Nutri-Score, an indicator of nutritional quality
Home-page: https://github.com/lemonhead94/pyNutriScore
Author: Jorit Studer
Author-email: jorit.studer@gmail.com
License: UNKNOWN
Platform: UNKNOWN
Classifier: Programming Language :: Python :: 3
Classifier: License :: OSI Approved :: MIT License
Classifier: Operating System :: OS Independent
Requires-Python: >=3.7
License-File: LICENSE
